slack_log_handler/__init__.py
slack_log_handler-0.3.0.dist-info/DESCRIPTION.rst
slack_log_handler-0.3.0.dist-info/METADATA
slack_log_handler-0.3.0.dist-info/RECORD
slack_log_handler-0.3.0.dist-info/WHEEL
slack_log_handler-0.3.0.dist-info/metadata.json
slack_log_handler-0.3.0.dist-info/top_level.txt
