Metadata-Version: 2.0
Name: slack-log-handler
Version: 0.3.0
Summary: Python Slack log handler using webhook
Home-page: https://github.com/claudetech/python-slack-log
Author: Daniel Perez
Author-email: daniel@claudetech.com
License: LICENSE
Platform: UNKNOWN
Classifier: Development Status :: 4 - Beta
Classifier: Intended Audience :: Developers
Classifier: License :: OSI Approved :: MIT License
Classifier: Operating System :: OS Independent
Classifier: Programming Language :: Python
Classifier: Topic :: Software Development :: Libraries
